{
	"id": "oval:com.ubuntu.focal:var:594710000000",
	"version": "1",
	"datatype": "string",
	"comment": "Available with Ubuntu Pro: https://ubuntu.com/pro",
	"value": [
		"^php-twig-inky-extra(?::\\w+|)\\s+(.*)$",
		"^php-twig-cssinliner-extra(?::\\w+|)\\s+(.*)$",
		"^php-twig-intl-extra(?::\\w+|)\\s+(.*)$",
		"^php-twig-extra-bundle(?::\\w+|)\\s+(.*)$",
		"^php-twig-html-extra(?::\\w+|)\\s+(.*)$",
		"^php-twig-doc(?::\\w+|)\\s+(.*)$",
		"^php-twig-markdown-extra(?::\\w+|)\\s+(.*)$",
		"^php-twig(?::\\w+|)\\s+(.*)$"
	]
}
