{
	"id": "oval:com.ubuntu.trusty:var:14040192500020",
	"version": "1",
	"datatype": "string",
	"comment": "The 'sssd' package binaries",
	"value": [
		"^libipa-hbac0(?::\\w+|)\\s+(.*)$",
		"^libnss-sss(?::\\w+|)\\s+(.*)$",
		"^libpam-sss(?::\\w+|)\\s+(.*)$",
		"^libsss-idmap0(?::\\w+|)\\s+(.*)$",
		"^libsss-nss-idmap0(?::\\w+|)\\s+(.*)$",
		"^libsss-sudo(?::\\w+|)\\s+(.*)$",
		"^python-libipa-hbac(?::\\w+|)\\s+(.*)$",
		"^python-libsss-nss-idmap(?::\\w+|)\\s+(.*)$",
		"^python-sss(?::\\w+|)\\s+(.*)$",
		"^sssd(?::\\w+|)\\s+(.*)$",
		"^sssd-ad(?::\\w+|)\\s+(.*)$",
		"^sssd-ad-common(?::\\w+|)\\s+(.*)$",
		"^sssd-common(?::\\w+|)\\s+(.*)$",
		"^sssd-dbus(?::\\w+|)\\s+(.*)$",
		"^sssd-ipa(?::\\w+|)\\s+(.*)$",
		"^sssd-krb5(?::\\w+|)\\s+(.*)$",
		"^sssd-krb5-common(?::\\w+|)\\s+(.*)$",
		"^sssd-ldap(?::\\w+|)\\s+(.*)$",
		"^sssd-proxy(?::\\w+|)\\s+(.*)$",
		"^sssd-tools(?::\\w+|)\\s+(.*)$"
	]
}
