{
	"id": "oval:com.ubuntu.xenial:var:16040188700000",
	"version": "1",
	"datatype": "string",
	"comment": "The 'rpm' package binaries",
	"value": [
		"^debugedit(?::\\w+|)\\s+(.*)$",
		"^librpm3(?::\\w+|)\\s+(.*)$",
		"^librpmbuild3(?::\\w+|)\\s+(.*)$",
		"^librpmio3(?::\\w+|)\\s+(.*)$",
		"^librpmsign3(?::\\w+|)\\s+(.*)$",
		"^python-rpm(?::\\w+|)\\s+(.*)$",
		"^python3-rpm(?::\\w+|)\\s+(.*)$",
		"^rpm(?::\\w+|)\\s+(.*)$",
		"^rpm-common(?::\\w+|)\\s+(.*)$",
		"^rpm-i18n(?::\\w+|)\\s+(.*)$",
		"^rpm2cpio(?::\\w+|)\\s+(.*)$"
	]
}
