{
	"id": "oval:com.ubuntu.xenial:var:201374470000010",
	"version": "1",
	"datatype": "string",
	"comment": "The 'gambas3' package binaries",
	"value": [
		"^gambas3(?::\\w+|)\\s+(.*)$",
		"^gambas3-gb-args(?::\\w+|)\\s+(.*)$",
		"^gambas3-gb-cairo(?::\\w+|)\\s+(.*)$",
		"^gambas3-gb-chart(?::\\w+|)\\s+(.*)$",
		"^gambas3-gb-clipper(?::\\w+|)\\s+(.*)$",
		"^gambas3-gb-complex(?::\\w+|)\\s+(.*)$",
		"^gambas3-gb-compress(?::\\w+|)\\s+(.*)$",
		"^gambas3-gb-compress-bzlib2(?::\\w+|)\\s+(.*)$",
		"^gambas3-gb-compress-zlib(?::\\w+|)\\s+(.*)$",
		"^gambas3-gb-crypt(?::\\w+|)\\s+(.*)$",
		"^gambas3-gb-data(?::\\w+|)\\s+(.*)$",
		"^gambas3-gb-db(?::\\w+|)\\s+(.*)$",
		"^gambas3-gb-db-form(?::\\w+|)\\s+(.*)$",
		"^gambas3-gb-db-mysql(?::\\w+|)\\s+(.*)$",
		"^gambas3-gb-db-odbc(?::\\w+|)\\s+(.*)$",
		"^gambas3-gb-db-postgresql(?::\\w+|)\\s+(.*)$",
		"^gambas3-gb-db-sqlite3(?::\\w+|)\\s+(.*)$",
		"^gambas3-gb-dbus(?::\\w+|)\\s+(.*)$",
		"^gambas3-gb-desktop(?::\\w+|)\\s+(.*)$",
		"^gambas3-gb-desktop-gnome(?::\\w+|)\\s+(.*)$",
		"^gambas3-gb-desktop-gnome-keyring(?::\\w+|)\\s+(.*)$",
		"^gambas3-gb-desktop-x11(?::\\w+|)\\s+(.*)$",
		"^gambas3-gb-eval-highlight(?::\\w+|)\\s+(.*)$",
		"^gambas3-gb-form(?::\\w+|)\\s+(.*)$",
		"^gambas3-gb-form-dialog(?::\\w+|)\\s+(.*)$",
		"^gambas3-gb-form-editor(?::\\w+|)\\s+(.*)$",
		"^gambas3-gb-form-mdi(?::\\w+|)\\s+(.*)$",
		"^gambas3-gb-form-stock(?::\\w+|)\\s+(.*)$",
		"^gambas3-gb-gmp(?::\\w+|)\\s+(.*)$",
		"^gambas3-gb-gsl(?::\\w+|)\\s+(.*)$",
		"^gambas3-gb-gtk(?::\\w+|)\\s+(.*)$",
		"^gambas3-gb-gtk-opengl(?::\\w+|)\\s+(.*)$",
		"^gambas3-gb-gtk3(?::\\w+|)\\s+(.*)$",
		"^gambas3-gb-gui(?::\\w+|)\\s+(.*)$",
		"^gambas3-gb-gui-opengl(?::\\w+|)\\s+(.*)$",
		"^gambas3-gb-gui-qt(?::\\w+|)\\s+(.*)$",
		"^gambas3-gb-gui-qt-webkit(?::\\w+|)\\s+(.*)$",
		"^gambas3-gb-gui-trayicon(?::\\w+|)\\s+(.*)$",
		"^gambas3-gb-httpd(?::\\w+|)\\s+(.*)$",
		"^gambas3-gb-image(?::\\w+|)\\s+(.*)$",
		"^gambas3-gb-image-effect(?::\\w+|)\\s+(.*)$",
		"^gambas3-gb-image-imlib(?::\\w+|)\\s+(.*)$",
		"^gambas3-gb-image-io(?::\\w+|)\\s+(.*)$",
		"^gambas3-gb-inotify(?::\\w+|)\\s+(.*)$",
		"^gambas3-gb-jit(?::\\w+|)\\s+(.*)$",
		"^gambas3-gb-libxml(?::\\w+|)\\s+(.*)$",
		"^gambas3-gb-logging(?::\\w+|)\\s+(.*)$",
		"^gambas3-gb-map(?::\\w+|)\\s+(.*)$",
		"^gambas3-gb-markdown(?::\\w+|)\\s+(.*)$",
		"^gambas3-gb-media(?::\\w+|)\\s+(.*)$",
		"^gambas3-gb-memcached(?::\\w+|)\\s+(.*)$",
		"^gambas3-gb-mime(?::\\w+|)\\s+(.*)$",
		"^gambas3-gb-mysql(?::\\w+|)\\s+(.*)$",
		"^gambas3-gb-ncurses(?::\\w+|)\\s+(.*)$",
		"^gambas3-gb-net(?::\\w+|)\\s+(.*)$",
		"^gambas3-gb-net-curl(?::\\w+|)\\s+(.*)$",
		"^gambas3-gb-net-pop3(?::\\w+|)\\s+(.*)$",
		"^gambas3-gb-net-smtp(?::\\w+|)\\s+(.*)$",
		"^gambas3-gb-openal(?::\\w+|)\\s+(.*)$",
		"^gambas3-gb-opengl(?::\\w+|)\\s+(.*)$",
		"^gambas3-gb-opengl-glsl(?::\\w+|)\\s+(.*)$",
		"^gambas3-gb-opengl-glu(?::\\w+|)\\s+(.*)$",
		"^gambas3-gb-opengl-sge(?::\\w+|)\\s+(.*)$",
		"^gambas3-gb-openssl(?::\\w+|)\\s+(.*)$",
		"^gambas3-gb-option(?::\\w+|)\\s+(.*)$",
		"^gambas3-gb-pcre(?::\\w+|)\\s+(.*)$",
		"^gambas3-gb-pdf(?::\\w+|)\\s+(.*)$",
		"^gambas3-gb-qt4(?::\\w+|)\\s+(.*)$",
		"^gambas3-gb-qt4-ext(?::\\w+|)\\s+(.*)$",
		"^gambas3-gb-qt4-opengl(?::\\w+|)\\s+(.*)$",
		"^gambas3-gb-qt5(?::\\w+|)\\s+(.*)$",
		"^gambas3-gb-qt5-opengl(?::\\w+|)\\s+(.*)$",
		"^gambas3-gb-qt5-webkit(?::\\w+|)\\s+(.*)$",
		"^gambas3-gb-report(?::\\w+|)\\s+(.*)$",
		"^gambas3-gb-report2(?::\\w+|)\\s+(.*)$",
		"^gambas3-gb-scanner(?::\\w+|)\\s+(.*)$",
		"^gambas3-gb-sdl(?::\\w+|)\\s+(.*)$",
		"^gambas3-gb-sdl-sound(?::\\w+|)\\s+(.*)$",
		"^gambas3-gb-sdl2(?::\\w+|)\\s+(.*)$",
		"^gambas3-gb-sdl2-audio(?::\\w+|)\\s+(.*)$",
		"^gambas3-gb-settings(?::\\w+|)\\s+(.*)$",
		"^gambas3-gb-signal(?::\\w+|)\\s+(.*)$",
		"^gambas3-gb-util(?::\\w+|)\\s+(.*)$",
		"^gambas3-gb-util-web(?::\\w+|)\\s+(.*)$",
		"^gambas3-gb-v4l(?::\\w+|)\\s+(.*)$",
		"^gambas3-gb-vb(?::\\w+|)\\s+(.*)$",
		"^gambas3-gb-web(?::\\w+|)\\s+(.*)$",
		"^gambas3-gb-xml(?::\\w+|)\\s+(.*)$",
		"^gambas3-gb-xml-html(?::\\w+|)\\s+(.*)$",
		"^gambas3-gb-xml-rpc(?::\\w+|)\\s+(.*)$",
		"^gambas3-gb-xml-xslt(?::\\w+|)\\s+(.*)$",
		"^gambas3-ide(?::\\w+|)\\s+(.*)$",
		"^gambas3-runtime(?::\\w+|)\\s+(.*)$",
		"^gambas3-script(?::\\w+|)\\s+(.*)$",
		"^gambas3-templates(?::\\w+|)\\s+(.*)$"
	]
}
