{
  "id": "oval:com.ubuntu.trusty:var:201612350000000",
  "version": "1",
  "datatype": "string",
  "comment": "'oar' package binaries",
  "Value": [
    "^liboar-perl(?::\\w+|)\\s+(.*)$",
    "^oar-admin(?::\\w+|)\\s+(.*)$",
    "^oar-api(?::\\w+|)\\s+(.*)$",
    "^oar-common(?::\\w+|)\\s+(.*)$",
    "^oar-node(?::\\w+|)\\s+(.*)$",
    "^oar-restful-api(?::\\w+|)\\s+(.*)$",
    "^oar-server(?::\\w+|)\\s+(.*)$",
    "^oar-server-mysql(?::\\w+|)\\s+(.*)$",
    "^oar-server-pgsql(?::\\w+|)\\s+(.*)$",
    "^oar-user(?::\\w+|)\\s+(.*)$",
    "^oar-user-mysql(?::\\w+|)\\s+(.*)$",
    "^oar-user-pgsql(?::\\w+|)\\s+(.*)$",
    "^oar-web-status(?::\\w+|)\\s+(.*)$"
  ]
}
