{
	"class": "patch",
	"id": "oval:com.ubuntu.trusty:def:24751000000",
	"version": "1",
	"metadata": {
		"title": "USN-2475-1 -- GTK+ update",
		"description": "Clemens Fries discovered that GTK+ allowed bypassing certain screen locks by using the menu key. An attacker with physical access could possibly use this flaw to gain access to a locked session.  Update Instructions:  Run `sudo pro fix USN-2475-1` to fix the vulnerability. The problem can be corrected by updating your system to the following package versions:  libgtk-3-0-udeb - 3.10.8-0ubuntu1.4 libgail-3-0 - 3.10.8-0ubuntu1.4 gtk-3-examples - 3.10.8-0ubuntu1.4 libgtk-3-0 - 3.10.8-0ubuntu1.4 gir1.2-gtk-3.0 - 3.10.8-0ubuntu1.4 libgail-3-dev - 3.10.8-0ubuntu1.4 libgtk-3-common - 3.10.8-0ubuntu1.4 libgail-3-doc - 3.10.8-0ubuntu1.4 libgtk-3-doc - 3.10.8-0ubuntu1.4 libgtk-3-bin - 3.10.8-0ubuntu1.4 libgtk-3-dev - 3.10.8-0ubuntu1.4 No subscription required",
		"affected": {
			"family": "unix",
			"platform": "Ubuntu 14.04 LTS"
		},
		"reference": [
			{
				"source": "USN",
				"ref_id": "USN-2475-1",
				"ref_url": "https://ubuntu.com/security/notices/USN-2475-1"
			}
		],
		"advisory": {
			"from": "security@ubuntu.com",
			"severity": "None",
			"issued": {
				"date": "2015-01-15"
			},
			"bug": [
				"https://launchpad.net/bugs/1366790"
			]
		}
	},
	"criteria": {
		"criterias": [
			{
				"operator": "OR",
				"criterions": [
					{
						"test_ref": "oval:com.ubuntu.trusty:tst:247510000000",
						"comment": "Long Term Support"
					}
				]
			}
		]
	}
}
