{
	"id": "oval:com.ubuntu.impish:var:2020138440000000",
	"version": "1",
	"datatype": "string",
	"comment": "'gcc-10' package binaries",
	"value": [
		"^cpp-10\\s+(.*)",
		"^g++-10\\s+(.*)",
		"^g++-10-multilib\\s+(.*)",
		"^gcc-10\\s+(.*)",
		"^gcc-10-base\\s+(.*)",
		"^gcc-10-hppa64-linux-gnu\\s+(.*)",
		"^gcc-10-locales\\s+(.*)",
		"^gcc-10-multilib\\s+(.*)",
		"^gcc-10-offload-amdgcn\\s+(.*)",
		"^gcc-10-offload-nvptx\\s+(.*)",
		"^gcc-10-source\\s+(.*)",
		"^gcc-10-test-results\\s+(.*)",
		"^gccbrig-10\\s+(.*)",
		"^gccgo-10\\s+(.*)",
		"^gccgo-10-multilib\\s+(.*)",
		"^gdc-10\\s+(.*)",
		"^gdc-10-multilib\\s+(.*)",
		"^gfortran-10\\s+(.*)",
		"^gfortran-10-multilib\\s+(.*)",
		"^gm2-10\\s+(.*)",
		"^gnat-10\\s+(.*)",
		"^gobjc++-10\\s+(.*)",
		"^gobjc++-10-multilib\\s+(.*)",
		"^gobjc-10\\s+(.*)",
		"^gobjc-10-multilib\\s+(.*)",
		"^lib32go16\\s+(.*)",
		"^lib32gphobos1\\s+(.*)",
		"^lib64go16\\s+(.*)",
		"^lib64gphobos1\\s+(.*)",
		"^libgm2-15\\s+(.*)",
		"^libgnat-10\\s+(.*)",
		"^libgnat-util10\\s+(.*)",
		"^libgo16\\s+(.*)",
		"^libgomp-plugin-hsa1\\s+(.*)",
		"^libgphobos1\\s+(.*)",
		"^libstdc++-10-pic\\s+(.*)",
		"^libx32go16\\s+(.*)",
		"^libx32gphobos1\\s+(.*)"
	]
}
