{
	"id": "oval:com.ubuntu.impish:var:2019101430000000",
	"version": "1",
	"datatype": "string",
	"comment": "'freeradius' package binaries",
	"Value": [
		"^freeradius\\s+(.*)",
		"^freeradius-common\\s+(.*)",
		"^freeradius-config\\s+(.*)",
		"^freeradius-dhcp\\s+(.*)",
		"^freeradius-iodbc\\s+(.*)",
		"^freeradius-krb5\\s+(.*)",
		"^freeradius-ldap\\s+(.*)",
		"^freeradius-memcached\\s+(.*)",
		"^freeradius-mysql\\s+(.*)",
		"^freeradius-postgresql\\s+(.*)",
		"^freeradius-python3\\s+(.*)",
		"^freeradius-redis\\s+(.*)",
		"^freeradius-rest\\s+(.*)",
		"^freeradius-utils\\s+(.*)",
		"^freeradius-yubikey\\s+(.*)",
		"^libfreeradius3\\s+(.*)"
	]
}
