{
  "id": "oval:com.ubuntu.impish:var:201266180000000",
  "version": "1",
  "datatype": "string",
  "comment": "'ffmpeg' package binaries",
  "Value": [
    "^ffmpeg\\s+(.*)",
    "^libavcodec-extra\\s+(.*)",
    "^libavcodec-extra58\\s+(.*)",
    "^libavcodec58\\s+(.*)",
    "^libavdevice58\\s+(.*)",
    "^libavfilter-extra\\s+(.*)",
    "^libavfilter-extra7\\s+(.*)",
    "^libavfilter7\\s+(.*)",
    "^libavformat-extra\\s+(.*)",
    "^libavformat-extra58\\s+(.*)",
    "^libavformat58\\s+(.*)",
    "^libavutil56\\s+(.*)",
    "^libpostproc55\\s+(.*)",
    "^libswresample3\\s+(.*)",
    "^libswscale5\\s+(.*)"
  ]
}
