{
	"class": "patch",
	"id": "oval:com.ubuntu.bionic:def:39691000000",
	"version": "1",
	"metadata": {
		"title": "USN-3969-1 -- wpa_supplicant and hostapd vulnerability",
		"description": "It was discovered that wpa_supplicant and hostapd incorrectly handled unexpected fragments when using EAP-pwd. A remote attacker could possibly use this issue to cause a denial of service.  Update Instructions:  Run `sudo pro fix USN-3969-1` to fix the vulnerability. The problem can be corrected by updating your system to the following package versions:  hostapd - 2:2.6-15ubuntu2.3 wpagui - 2:2.6-15ubuntu2.3 wpasupplicant-udeb - 2:2.6-15ubuntu2.3 wpasupplicant - 2:2.6-15ubuntu2.3 No subscription required",
		"affected": {
			"family": "unix",
			"platform": "Ubuntu 18.04 LTS"
		},
		"reference": [
			{
				"source": "USN",
				"ref_id": "USN-3969-1",
				"ref_url": "https://ubuntu.com/security/notices/USN-3969-1"
			}
		],
		"advisory": {
			"from": "security@ubuntu.com",
			"severity": "None",
			"issued": {
				"date": "2019-05-07"
			}
		}
	},
	"criteria": {
		"criterias": [
			{
				"operator": "OR",
				"criterions": [
					{
						"test_ref": "oval:com.ubuntu.bionic:tst:396910000000",
						"comment": "Long Term Support"
					}
				]
			}
		]
	}
}
